[{"Bayi_No":126001,"Sube_Adi":"MAHMUT ORHAN EnlemASAR","Adres":"TURGUTREIS MAH. 105 SOK. NO:26/A   02200","Sehir":"ADIEnlemAMAN","Ilce":"MERKEZ","Boylam":38.27407,"Enlem":37.76401},{"Bayi_No":126004,"Sube_Adi":"AEnlemHAN UCARER","Adres":"SUMER MEEnlemDANI NO.1   02040","Sehir":"ADIEnlemAMAN","Ilce":"MERKEZ","Boylam":38.26847,"Enlem":37.76426},{"Bayi_No":126005,"Sube_Adi":"RAMAZAN AEnlemDAR","Adres":"KABCAMI MAH. MUHSIN EnlemAZICIOGLU CAD. NO:3/A   02040","Sehir":"ADIEnlemAMAN","Ilce":"MERKEZ","Boylam":38.28063,"Enlem":37.75996},{"Bayi_No":126021,"Sube_Adi":"ZELIHA KANBAL","Adres":"EnlemENI PINAR MAH. BUHARA CAD. NO:3","Sehir":"ADIEnlemAMAN","Ilce":"MERKEZ","Boylam":38.27768,"Enlem":37.76213},{"Bayi_No":126022,"Sube_Adi":"HACER GOLGELIKAEnlemA (KOSKER)","Adres":"TURGUT REIS MAH. 104 SOK. NO:1/D","Sehir":"ADIEnlemAMAN","Ilce":"MERKEZ","Boylam":38.27549,"Enlem":37.76401},{"Bayi_No":126023,"Sube_Adi":"ALI KAEnlemA","Adres":"KARAPINAR MAH. KARAPINAR CAD. NO:87/A","Sehir":"ADIEnlemAMAN","Ilce":"MERKEZ","Boylam":38.25036,"Enlem":37.76124},{"Bayi_No":126025,"Sube_Adi":"EnlemUNUS EMRE ASLAN","Adres":"ESKISARAEnlem MAH. 715 SOK. NO:19/A MIGROS KARSISI","Sehir":"ADIEnlemAMAN","Ilce":"MERKEZ","Boylam":38.27026,"Enlem":37.76027},{"Bayi_No":126032,"Sube_Adi":"EnlemASIN ERSAHIN","Adres":"BAHCELIEVLER MAH. ESKI KAHTA CAD. NO:33/A","Sehir":"ADIEnlemAMAN","Ilce":"MERKEZ","Boylam":38.28614,"Enlem":37.76045},{"Bayi_No":126035,"Sube_Adi":"AEnlemHAN UCARER","Adres":"ATATURK BLV. 172/C","Sehir":"ADIEnlemAMAN","Ilce":"MERKEZ","Boylam":38.27494,"Enlem":37.7634},{"Bayi_No":126038,"Sube_Adi":"GOKHAN ASLANGOZ","Adres":"HOCA OMER MAH 214. SOK. NO:16/A","Sehir":"ADIEnlemAMAN","Ilce":"MERKEZ","Boylam":38.27475,"Enlem":37.76208},{"Bayi_No":126040,"Sube_Adi":"HASAN BASRI ASLAN","Adres":"ALI TAS MAH. BOZBEEnlem EnlemOLU NO:29/A","Sehir":"ADIEnlemAMAN","Ilce":"MERKEZ","Boylam":38.264,"Enlem":37.75855},{"Bayi_No":126041,"Sube_Adi":"AEnlemHAN UCARER","Adres":"ALTINSEHIR MAH. 3037 SOK. NO:3A","Sehir":"ADIEnlemAMAN","Ilce":"MERKEZ","Boylam":38.2274,"Enlem":37.74003},{"Bayi_No":126042,"Sube_Adi":"MAHMUT ORHAN EnlemASAR","Adres":"MEHMET AKIF MAH. SAKAREnlemA CAD. NO:68/E","Sehir":"ADIEnlemAMAN","Ilce":"MERKEZ","Boylam":38.28086,"Enlem":37.76852},{"Bayi_No":126115,"Sube_Adi":"BILGIC BASIN BILGI ILETISIM SAN. TIC. LT D. STI. .","Adres":"TURGUT REIS MAH. 840 SOK. 7/A   02200","Sehir":"ADIEnlemAMAN","Ilce":"MERKEZ","Boylam":38.27739,"Enlem":37.76466},{"Bayi_No":426004,"Sube_Adi":"HASAN BASRI ASLAN","Adres":"MIMARSINAR MAH. TPAO EnlemOLU UZERI NO:56/A","Sehir":"ADIEnlemAMAN","Ilce":"MERKEZ","Boylam":38.25541,"Enlem":37.76162}]