[{"BayiNo":116301,"SubeAdi":"ISA KASAP","Adres":"GAZI CD. N.110   28100","Sehir":"GIRESUN","Ilce":"MERKEZ","Boylam":38.38937,"Enlem":40.91647},{"BayiNo":116312,"SubeAdi":"IBRAHIM KASAP","Adres":"GAZI CAD. NO:66   28200","Sehir":"GIRESUN","Ilce":"MERKEZ","Boylam":38.38814,"Enlem":40.91671},{"BayiNo":116317,"SubeAdi":"ISA YAMAK","Adres":"HACISIYAM MAH. FATIH CAD. 115/A   28200","Sehir":"GIRESUN","Ilce":"MERKEZ","Boylam":38.37981,"Enlem":40.91427},{"BayiNo":116324,"SubeAdi":"IBRAHIM OZKUL","Adres":"HACIMIKTAT MAH. ALPASLAN CAD. NO:19/B   28100","Sehir":"GIRESUN","Ilce":"MERKEZ","Boylam":38.38345,"Enlem":40.91676},{"BayiNo":116327,"SubeAdi":"NEVZAT ELMALI","Adres":"HACI MITHAT MAH. DERVISOGLU SOK. NO:26   28200","Sehir":"GIRESUN","Ilce":"MERKEZ","Boylam":38.38341,"Enlem":40.91585},{"BayiNo":116328,"SubeAdi":"MAHMUT TAHMAZOGLU","Adres":"KAPU MAHALLESI BEKIRPASA CADDESI NO:32/C","Sehir":"GIRESUN","Ilce":"MERKEZ","Boylam":38.38699,"Enlem":40.91848},{"BayiNo":116335,"SubeAdi":"SEVINC GIDA PAZ. SAN. LTD. STI.","Adres":"SULTAN SELIM MH. ESKIYAGCILAR SK. NO:9/D","Sehir":"GIRESUN","Ilce":"MERKEZ","Boylam":38.38491,"Enlem":40.91785},{"BayiNo":116338,"SubeAdi":"ADNAN AYDIN","Adres":"HACIHUSEYIN MAH. GAZI CAD. NO:225/A","Sehir":"GIRESUN","Ilce":"MERKEZ","Boylam":38.39453,"Enlem":40.91468},{"BayiNo":416312,"SubeAdi":"MERAL ATAMER","Adres":"HACI HUSEYIN MAH. GAZI MUSTAFA KEMAL BULV. NO:92","Sehir":"GIRESUN","Ilce":"MERKEZ","Boylam":38.43384,"Enlem":40.91186},{"BayiNo":416315,"SubeAdi":"SUKRAN SALMAN","Adres":"TAYYAREDUZU MAH. BOZTEKE CAD. NO:26/A","Sehir":"GIRESUN","Ilce":"MERKEZ","Boylam":38.33491,"Enlem":40.91439},{"BayiNo":416317,"SubeAdi":"ASKIN CAKIR","Adres":"HACIMIKTAT MAH. CEMAL GURSEL CAD. NO:91/B","Sehir":"GIRESUN","Ilce":"MERKEZ","Boylam":38.38294,"Enlem":40.91491},{"BayiNo":416324,"SubeAdi":"ARSLAN YILMAZ","Adres":"GEDIKKAYA MAH. ATATURK BLV. NO:206","Sehir":"GIRESUN","Ilce":"MERKEZ","Boylam":38.41673,"Enlem":40.91446},{"BayiNo":416809,"SubeAdi":"MUSTAFA YAYLA","Adres":"HACI HUSEYIN MAH. FEVZI PASA CAD. NO:51/C","Sehir":"GIRESUN","Ilce":"MERKEZ","Boylam":38.39355,"Enlem":40.9192}]