[{"Bayi_No":123001,"Sube_Adi":"FERIT CALIS","Adres":"ISTIKLAL CAD. NO.85   33070","Sehir":"MERSIN","Ilce":"AKDENIZ","Boylam":34.62325,"Enlem":36.79564},{"Bayi_No":123002,"Sube_Adi":"SABAHAT EZICI","Adres":"ZEYTINLI BAHCE CD. METROPOL IS MERKEZI D BLOK NO.90/K   33070","Sehir":"MERSIN","Ilce":"AKDENIZ","Boylam":34.62324,"Enlem":36.80304},{"Bayi_No":123005,"Sube_Adi":"HATICE DOGAN","Adres":"CAMI SERIF MH. ISTIKLAL CD. NO.37/C   33060","Sehir":"MERSIN","Ilce":"AKDENIZ","Boylam":34.62918,"Enlem":36.79973},{"Bayi_No":123006,"Sube_Adi":"HAYDAR KEMAL USTUN","Adres":"YENI HAL KOMPLEKSI, COK AMACLI DUKKANLAR A BLOK NO.8   33160","Sehir":"MERSIN","Ilce":"AKDENIZ","Boylam":34.65722,"Enlem":36.83059},{"Bayi_No":123017,"Sube_Adi":"MEHMET HANIFI INCE","Adres":"SITELER MAH. 160. CAD. 3/C   33040","Sehir":"MERSIN","Ilce":"AKDENIZ","Boylam":34.6413,"Enlem":36.81268},{"Bayi_No":123018,"Sube_Adi":"SULEYMAN MESUT OZER","Adres":"CAMISERIF MH. URAY CD. 25/E   33060","Sehir":"MERSIN","Ilce":"AKDENIZ","Boylam":34.63132,"Enlem":36.79915},{"Bayi_No":123019,"Sube_Adi":"SUNE GIDA LTD. STI. .","Adres":"KULTUR MH. CENGIZ TOPEL CD. 10/B CAMLIBEL   33010","Sehir":"MERSIN","Ilce":"AKDENIZ","Boylam":34.62248,"Enlem":36.78979},{"Bayi_No":123021,"Sube_Adi":"ALI DEKE","Adres":"MESUDIYE MAH. CAKMAK CAD. NO:63/C   33050","Sehir":"MERSIN","Ilce":"AKDENIZ","Boylam":34.62853,"Enlem":36.80672},{"Bayi_No":123027,"Sube_Adi":"HIKMET KURT","Adres":"IHSANIYE MAH. KUVAI MILLIYE CAD.NO:157/A   33100","Sehir":"MERSIN","Ilce":"AKDENIZ","Boylam":34.62176,"Enlem":36.80802},{"Bayi_No":123030,"Sube_Adi":"SIDIKA PEKER","Adres":"NUSRATIYE MH. 161 CD. NO.29/C   33190","Sehir":"MERSIN","Ilce":"AKDENIZ","Boylam":34.62879,"Enlem":36.81107},{"Bayi_No":123031,"Sube_Adi":"MEHMET IGDIR","Adres":"KARADUVAR MAH.DUMLUPINAR CAD.NO:22   33010","Sehir":"MERSIN","Ilce":"AKDENIZ","Boylam":34.69122,"Enlem":36.80985},{"Bayi_No":123032,"Sube_Adi":"ARIF NECMI BAYKAL","Adres":"CANKAYA MH. 4711 SOKAK NO 5/A   33010","Sehir":"MERSIN","Ilce":"AKDENIZ","Boylam":34.62871,"Enlem":36.79789},{"Bayi_No":123041,"Sube_Adi":"MAHMUT TEKIN ERDOGAN","Adres":"CANKAYA MAH. SOGUKSU CAD. NO:27   33200","Sehir":"MERSIN","Ilce":"AKDENIZ","Boylam":34.62777,"Enlem":36.79727},{"Bayi_No":123044,"Sube_Adi":"HABIB AKSIN","Adres":"CAKMAK CAD. MESUDIYE MAH. NO:31/C   33050","Sehir":"MERSIN","Ilce":"AKDENIZ","Boylam":34.63073,"Enlem":36.80444},{"Bayi_No":123048,"Sube_Adi":"ABDULLAH KOC","Adres":"HAMIDIYE MAH. SILIFKE CAD. NO:161/B   33050","Sehir":"MERSIN","Ilce":"AKDENIZ","Boylam":34.61625,"Enlem":36.78841},{"Bayi_No":123074,"Sube_Adi":"ERHAN GURSEN","Adres":"KIREMITHANE MAH SILIFKE CAD GOKSEL APT ALTI NO:62   33070","Sehir":"MERSIN","Ilce":"AKDENIZ","Boylam":34.62288,"Enlem":36.79389},{"Bayi_No":123106,"Sube_Adi":"SULEYMAN INCE","Adres":"IHSANIYE MAH. 123.CAD. (Z.BAHCE) NO:122","Sehir":"MERSIN","Ilce":"AKDENIZ","Boylam":34.62075,"Enlem":36.80505},{"Bayi_No":123119,"Sube_Adi":"ERSIN GUVEN","Adres":"YENIMAHALLE ATATURK CD. NO:90 KAZANLI","Sehir":"MERSIN","Ilce":"AKDENIZ","Boylam":34.75214,"Enlem":36.81598},{"Bayi_No":123137,"Sube_Adi":"ISMAIL METIN","Adres":"BAHSIS MH. GAZI SK. NO:2 HUZURKENT AKDENIZ","Sehir":"MERSIN","Ilce":"AKDENIZ","Boylam":34.825,"Enlem":36.8806},{"Bayi_No":123157,"Sube_Adi":"MEHMET VEYSEL CAYKITER","Adres":"IHSANIYE MAH. KUVAYI MILLI CAD. 4901 SOK. AKARSU PLAZA NO:18","Sehir":"MERSIN","Ilce":"AKDENIZ","Boylam":34.62313,"Enlem":36.80464},{"Bayi_No":123168,"Sube_Adi":"FIRAT GULER","Adres":"YENI MAH. 5319 SK. ATAMER APT. ALTI NO:18/A","Sehir":"MERSIN","Ilce":"AKDENIZ","Boylam":34.63398,"Enlem":36.80716},{"Bayi_No":123187,"Sube_Adi":"GULUMSER OYA ALTUNPINAR","Adres":"CANKAYA MAH. 4726 SOK. NO:6/B","Sehir":"MERSIN","Ilce":"AKDENIZ","Boylam":34.6277,"Enlem":36.79937},{"Bayi_No":123197,"Sube_Adi":"BUFE 2000 SANS OYUNLARI TEKEL GIDA SAN.TIC.LTD.STI.","Adres":"CAMI SERIF MAH. ISTIKLAL CAD. NO:24/B","Sehir":"MERSIN","Ilce":"AKDENIZ","Boylam":34.63217,"Enlem":36.80157},{"Bayi_No":123206,"Sube_Adi":"SUNE GIDA INS. SANS OYUN. TIC.LTD.STI.","Adres":"PIRIREIS MAH.SILIFKE CAD.NO:454/B","Sehir":"MERSIN","Ilce":"AKDENIZ","Boylam":34.61117,"Enlem":36.78771},{"Bayi_No":123208,"Sube_Adi":"DIYAR KILICTEPE","Adres":"BAHCE MAH. 4602 SOK. NO:7/E","Sehir":"MERSIN","Ilce":"AKDENIZ","Boylam":34.62478,"Enlem":36.79764},{"Bayi_No":423055,"Sube_Adi":"GIZEM SIRIM","Adres":"TURGUT REIS MAH. CENGIZ TOPEL CAD. NO:79/B","Sehir":"MERSIN","Ilce":"AKDENIZ","Boylam":34.61718,"Enlem":36.79497},{"Bayi_No":423056,"Sube_Adi":"ZEKERIYA ULAR","Adres":"GUNDOGDU MAH. 141 CD. NO:92/A","Sehir":"MERSIN","Ilce":"AKDENIZ","Boylam":34.64288,"Enlem":36.81832}]